erroi/__init__.py
erroi-0.1.0.dist-info/WHEEL
erroi-0.1.0.dist-info/METADATA
erroi-0.1.0.dist-info/RECORD
