Metadata-Version: 2.1
Name: erroi
Version: 0.1.0
Summary: ERRant Other Improver
Author: Aneta Melisa Stal
Author-email: melisa-qordoba@writer.com
Requires-Python: >=3.8,<4.0
Classifier: Programming Language :: Python :: 3
Classifier: Programming Language :: Python :: 3.8
Classifier: Programming Language :: Python :: 3.9
Requires-Dist: SoundsLike (>=0.0.11,<0.0.12)
